setup.py
fpkg/__init__.py
fpkg/code.py
fpkg.egg-info/PKG-INFO
fpkg.egg-info/SOURCES.txt
fpkg.egg-info/dependency_links.txt
fpkg.egg-info/not-zip-safe
fpkg.egg-info/top_level.txt