Metadata-Version: 1.0
Name: fpkg
Version: 0.1
Summary: A pkg utility
Home-page: http://github.com/ewencp/foo
Author: amoschang
Author-email: amos@it.org
License: MIT
Platform: any
